dummy.cpython-313-darwin.so
falkordblite-0.7.0.data/scripts/redis-server
falkordblite-0.7.0.data/scripts/redis-cli
falkordblite-0.7.0.dist-info/RECORD
falkordblite-0.7.0.dist-info/WHEEL
falkordblite-0.7.0.dist-info/top_level.txt
falkordblite-0.7.0.dist-info/METADATA
falkordblite-0.7.0.dist-info/licenses/LICENSE.txt
redislite/patch.py
redislite/configuration.py
redislite/client.py
redislite/__init__.py
redislite/debug.py
redislite/async_client.py
redislite/falkordb_client.py
redislite/package_metadata.json
redislite/async_falkordb_client.py
redislite/bin/redis-server
redislite/bin/redis-cli
redislite/bin/falkordb.so
redislite/.dylibs/libssl.3.dylib
redislite/.dylibs/libomp.dylib
redislite/.dylibs/libcrypto.3.dylib
