Metadata-Version: 2.4
Name: falkordblite
Version: 0.7.0
Summary: FalkorDB embedded in a Python package
Home-page: https://github.com/FalkorDB/falkordblite
Author: FalkorDB
Author-email: roi@falkordb.com
License: BSD License
Project-URL: Homepage, https://www.falkordb.com/
Project-URL: Documentation, https://docs.falkordb.com/
Project-URL: Source, https://github.com/FalkorDB/falkordblite
Keywords: falkordb redis graph database cypher embedded python
Classifier: Development Status :: 4 - Beta
Classifier: Environment :: Console
Classifier: Intended Audience :: Developers
Classifier: License :: OSI Approved :: BSD License
Classifier: Operating System :: MacOS :: MacOS X
Classifier: Operating System :: POSIX :: Linux
Classifier: Operating System :: POSIX
Classifier: Programming Language :: C
Classifier: Programming Language :: Python :: 3
Classifier: Programming Language :: Python :: 3.12
Classifier: Programming Language :: Python :: 3.13
Classifier: Programming Language :: Python :: 3.14
Classifier: Programming Language :: Python :: Implementation :: CPython
Classifier: Programming Language :: Python
Classifier: Topic :: Database
Classifier: Topic :: Software Development :: Libraries :: Python Modules
Classifier: Topic :: Software Development :: Libraries
Requires-Python: >=3.12.0
License-File: LICENSE.txt
Requires-Dist: redis>=4.5
Requires-Dist: falkordb>=1.2.0
Requires-Dist: psutil
Requires-Dist: setuptools>38.0
Dynamic: license-file
